<?xml version="1.0" encoding="utf-8"?>
<events version="1.0">
	<event time="21510.0" type="actend" person="3" link="1" actType="h"  />
	<event time="21510.0" type="departure" person="3" link="1" legMode="car"  />
	<event time="21510.0" type="PersonEntersVehicle" person="3" vehicle="3"  />
	<event time="21510.0" type="vehicle enters traffic" person="3" link="1" vehicle="3" networkMode="car" relativePosition="1.0"  />
	<event time="21511.0" type="left link" link="1" vehicle="3"  />
	<event time="21511.0" type="entered link" link="4" vehicle="3"  />
	<event time="21540.0" type="actend" person="2" link="1" actType="h"  />
	<event time="21540.0" type="departure" person="2" link="1" legMode="car"  />
	<event time="21540.0" type="PersonEntersVehicle" person="2" vehicle="2"  />
	<event time="21540.0" type="vehicle enters traffic" person="2" link="1" vehicle="2" networkMode="car" relativePosition="1.0"  />
	<event time="21541.0" type="left link" link="1" vehicle="2"  />
	<event time="21541.0" type="entered link" link="4" vehicle="2"  />
	<event time="21570.0" type="actend" person="4" link="1" actType="h"  />
	<event time="21570.0" type="departure" person="4" link="1" legMode="car"  />
	<event time="21570.0" type="PersonEntersVehicle" person="4" vehicle="4"  />
	<event time="21570.0" type="vehicle enters traffic" person="4" link="1" vehicle="4" networkMode="car" relativePosition="1.0"  />
	<event time="21571.0" type="left link" link="1" vehicle="4"  />
	<event time="21571.0" type="entered link" link="4" vehicle="4"  />
	<event time="21600.0" type="actend" person="9" link="1" actType="h"  />
	<event time="21600.0" type="departure" person="9" link="1" legMode="bicycle"  />
	<event time="21600.0" type="actend" person="8" link="1" actType="h"  />
	<event time="21600.0" type="departure" person="8" link="1" legMode="bicycle"  />
	<event time="21600.0" type="actend" person="7" link="1" actType="h"  />
	<event time="21600.0" type="departure" person="7" link="1" legMode="bicycle"  />
	<event time="21600.0" type="actend" person="6" link="1" actType="h"  />
	<event time="21600.0" type="departure" person="6" link="1" legMode="bicycle"  />
	<event time="21600.0" type="actend" person="5" link="1" actType="h"  />
	<event time="21600.0" type="departure" person="5" link="1" legMode="car"  />
	<event time="21600.0" type="PersonEntersVehicle" person="5" vehicle="5"  />
	<event time="21600.0" type="actend" person="10" link="1" actType="h"  />
	<event time="21600.0" type="departure" person="10" link="1" legMode="bicycle"  />
	<event time="21600.0" type="actend" person="1" link="1" actType="h"  />
	<event time="21600.0" type="departure" person="1" link="1" legMode="car"  />
	<event time="21600.0" type="PersonEntersVehicle" person="1" vehicle="1"  />
	<event time="21600.0" type="vehicle enters traffic" person="5" link="1" vehicle="5" networkMode="car" relativePosition="1.0"  />
	<event time="21600.0" type="vehicle enters traffic" person="1" link="1" vehicle="1" networkMode="car" relativePosition="1.0"  />
	<event time="21601.0" type="left link" link="1" vehicle="5"  />
	<event time="21601.0" type="entered link" link="3" vehicle="5"  />
	<event time="21601.0" type="left link" link="1" vehicle="1"  />
	<event time="21601.0" type="entered link" link="5" vehicle="1"  />
	<event time="22111.0" type="left link" link="4" vehicle="3"  />
	<event time="22111.0" type="entered link" link="13" vehicle="3"  />
	<event time="22140.0" type="travelled" person="9" distance="25000.0" mode="bicycle"  />
	<event time="22140.0" type="arrival" person="9" link="20" legMode="bicycle"  />
	<event time="22140.0" type="actstart" person="9" link="20" x="10000.0" y="0.0" actType="w"  />
	<event time="22140.0" type="travelled" person="8" distance="25000.0" mode="bicycle"  />
	<event time="22140.0" type="arrival" person="8" link="20" legMode="bicycle"  />
	<event time="22140.0" type="actstart" person="8" link="20" x="10000.0" y="0.0" actType="w"  />
	<event time="22140.0" type="travelled" person="7" distance="25000.0" mode="bicycle"  />
	<event time="22140.0" type="arrival" person="7" link="20" legMode="bicycle"  />
	<event time="22140.0" type="actstart" person="7" link="20" x="10000.0" y="0.0" actType="w"  />
	<event time="22140.0" type="travelled" person="6" distance="25000.0" mode="bicycle"  />
	<event time="22140.0" type="arrival" person="6" link="20" legMode="bicycle"  />
	<event time="22140.0" type="actstart" person="6" link="20" x="10000.0" y="0.0" actType="w"  />
	<event time="22140.0" type="travelled" person="10" distance="25000.0" mode="bicycle"  />
	<event time="22140.0" type="arrival" person="10" link="20" legMode="bicycle"  />
	<event time="22140.0" type="actstart" person="10" link="20" x="10000.0" y="0.0" actType="w"  />
	<event time="22201.0" type="left link" link="3" vehicle="5"  />
	<event time="22201.0" type="entered link" link="12" vehicle="5"  />
	<event time="22201.0" type="left link" link="5" vehicle="1"  />
	<event time="22201.0" type="entered link" link="14" vehicle="1"  />
	<event time="22411.0" type="left link" link="13" vehicle="3"  />
	<event time="22411.0" type="entered link" link="20" vehicle="3"  />
	<event time="22501.0" type="left link" link="14" vehicle="1"  />
	<event time="22501.0" type="entered link" link="20" vehicle="1"  />
	<event time="22501.0" type="left link" link="12" vehicle="5"  />
	<event time="22501.0" type="entered link" link="20" vehicle="5"  />
	<event time="23010.0" type="vehicle leaves traffic" person="3" link="20" vehicle="3" networkMode="car" relativePosition="1.0"  />
	<event time="23010.0" type="PersonLeavesVehicle" person="3" vehicle="3"  />
	<event time="23010.0" type="arrival" person="3" link="20" legMode="car"  />
	<event time="23010.0" type="actstart" person="3" link="20" x="10000.0" y="0.0" actType="w"  />
	<event time="23100.0" type="vehicle leaves traffic" person="5" link="20" vehicle="5" networkMode="car" relativePosition="1.0"  />
	<event time="23100.0" type="PersonLeavesVehicle" person="5" vehicle="5"  />
	<event time="23100.0" type="arrival" person="5" link="20" legMode="car"  />
	<event time="23100.0" type="actstart" person="5" link="20" x="10000.0" y="0.0" actType="w"  />
	<event time="23100.0" type="vehicle leaves traffic" person="1" link="20" vehicle="1" networkMode="car" relativePosition="1.0"  />
	<event time="23100.0" type="PersonLeavesVehicle" person="1" vehicle="1"  />
	<event time="23100.0" type="arrival" person="1" link="20" legMode="car"  />
	<event time="23100.0" type="actstart" person="1" link="20" x="10000.0" y="0.0" actType="w"  />
	<event time="23310.0" type="left link" link="4" vehicle="2"  />
	<event time="23310.0" type="entered link" link="13" vehicle="2"  />
	<event time="23610.0" type="left link" link="13" vehicle="2"  />
	<event time="23610.0" type="entered link" link="20" vehicle="2"  />
	<event time="23700.0" type="actend" person="1" link="20" actType="w"  />
	<event time="23700.0" type="departure" person="1" link="20" legMode="car"  />
	<event time="23700.0" type="PersonEntersVehicle" person="1" vehicle="1"  />
	<event time="23700.0" type="vehicle enters traffic" person="1" link="20" vehicle="1" networkMode="car" relativePosition="1.0"  />
	<event time="23701.0" type="left link" link="20" vehicle="1"  />
	<event time="23701.0" type="entered link" link="21" vehicle="1"  />
	<event time="23940.0" type="actend" person="9" link="20" actType="w"  />
	<event time="23940.0" type="departure" person="9" link="20" legMode="bicycle"  />
	<event time="23940.0" type="actend" person="8" link="20" actType="w"  />
	<event time="23940.0" type="departure" person="8" link="20" legMode="bicycle"  />
	<event time="23940.0" type="actend" person="7" link="20" actType="w"  />
	<event time="23940.0" type="departure" person="7" link="20" legMode="bicycle"  />
	<event time="23940.0" type="actend" person="6" link="20" actType="w"  />
	<event time="23940.0" type="departure" person="6" link="20" legMode="bicycle"  />
	<event time="23940.0" type="actend" person="10" link="20" actType="w"  />
	<event time="23940.0" type="departure" person="10" link="20" legMode="bicycle"  />
	<event time="24209.0" type="vehicle leaves traffic" person="2" link="20" vehicle="2" networkMode="car" relativePosition="1.0"  />
	<event time="24209.0" type="PersonLeavesVehicle" person="2" vehicle="2"  />
	<event time="24209.0" type="arrival" person="2" link="20" legMode="car"  />
	<event time="24209.0" type="actstart" person="2" link="20" x="10000.0" y="0.0" actType="w"  />
	<event time="24301.0" type="left link" link="21" vehicle="1"  />
	<event time="24301.0" type="entered link" link="22" vehicle="1"  />
	<event time="24510.0" type="left link" link="4" vehicle="4"  />
	<event time="24510.0" type="entered link" link="13" vehicle="4"  />
	<event time="24810.0" type="left link" link="13" vehicle="4"  />
	<event time="24810.0" type="entered link" link="20" vehicle="4"  />
	<event time="25409.0" type="vehicle leaves traffic" person="4" link="20" vehicle="4" networkMode="car" relativePosition="1.0"  />
	<event time="25409.0" type="PersonLeavesVehicle" person="4" vehicle="4"  />
	<event time="25409.0" type="arrival" person="4" link="20" legMode="car"  />
	<event time="25409.0" type="actstart" person="4" link="20" x="10000.0" y="0.0" actType="w"  />
	<event time="25920.0" type="travelled" person="9" distance="65000.0" mode="bicycle"  />
	<event time="25920.0" type="arrival" person="9" link="1" legMode="bicycle"  />
	<event time="25920.0" type="actstart" person="9" link="1" x="-25000.0" y="0.0" actType="h"  />
	<event time="25920.0" type="travelled" person="8" distance="65000.0" mode="bicycle"  />
	<event time="25920.0" type="arrival" person="8" link="1" legMode="bicycle"  />
	<event time="25920.0" type="actstart" person="8" link="1" x="-25000.0" y="0.0" actType="h"  />
	<event time="25920.0" type="travelled" person="7" distance="65000.0" mode="bicycle"  />
	<event time="25920.0" type="arrival" person="7" link="1" legMode="bicycle"  />
	<event time="25920.0" type="actstart" person="7" link="1" x="-25000.0" y="0.0" actType="h"  />
	<event time="25920.0" type="travelled" person="6" distance="65000.0" mode="bicycle"  />
	<event time="25920.0" type="arrival" person="6" link="1" legMode="bicycle"  />
	<event time="25920.0" type="actstart" person="6" link="1" x="-25000.0" y="0.0" actType="h"  />
	<event time="25920.0" type="travelled" person="10" distance="65000.0" mode="bicycle"  />
	<event time="25920.0" type="arrival" person="10" link="1" legMode="bicycle"  />
	<event time="25920.0" type="actstart" person="10" link="1" x="-25000.0" y="0.0" actType="h"  />
	<event time="26401.0" type="left link" link="22" vehicle="1"  />
	<event time="26401.0" type="entered link" link="23" vehicle="1"  />
	<event time="27001.0" type="left link" link="23" vehicle="1"  />
	<event time="27001.0" type="entered link" link="1" vehicle="1"  />
	<event time="27600.0" type="vehicle leaves traffic" person="1" link="1" vehicle="1" networkMode="car" relativePosition="1.0"  />
	<event time="27600.0" type="PersonLeavesVehicle" person="1" vehicle="1"  />
	<event time="27600.0" type="arrival" person="1" link="1" legMode="car"  />
	<event time="27600.0" type="actstart" person="1" link="1" x="-25000.0" y="0.0" actType="h"  />
	<event time="28410.0" type="actend" person="3" link="20" actType="w"  />
	<event time="28410.0" type="departure" person="3" link="20" legMode="car"  />
	<event time="28410.0" type="PersonEntersVehicle" person="3" vehicle="3"  />
	<event time="28410.0" type="vehicle enters traffic" person="3" link="20" vehicle="3" networkMode="car" relativePosition="1.0"  />
	<event time="28411.0" type="left link" link="20" vehicle="3"  />
	<event time="28411.0" type="entered link" link="21" vehicle="3"  />
	<event time="29011.0" type="left link" link="21" vehicle="3"  />
	<event time="29011.0" type="entered link" link="22" vehicle="3"  />
	<event time="31111.0" type="left link" link="22" vehicle="3"  />
	<event time="31111.0" type="entered link" link="23" vehicle="3"  />
	<event time="31711.0" type="left link" link="23" vehicle="3"  />
	<event time="31711.0" type="entered link" link="1" vehicle="3"  />
	<event time="32310.0" type="vehicle leaves traffic" person="3" link="1" vehicle="3" networkMode="car" relativePosition="1.0"  />
	<event time="32310.0" type="PersonLeavesVehicle" person="3" vehicle="3"  />
	<event time="32310.0" type="arrival" person="3" link="1" legMode="car"  />
	<event time="32310.0" type="actstart" person="3" link="1" x="-25000.0" y="0.0" actType="h"  />
	<event time="33209.0" type="actend" person="2" link="20" actType="w"  />
	<event time="33209.0" type="departure" person="2" link="20" legMode="car"  />
	<event time="33209.0" type="PersonEntersVehicle" person="2" vehicle="2"  />
	<event time="33209.0" type="vehicle enters traffic" person="2" link="20" vehicle="2" networkMode="car" relativePosition="1.0"  />
	<event time="33210.0" type="left link" link="20" vehicle="2"  />
	<event time="33210.0" type="entered link" link="21" vehicle="2"  />
	<event time="33810.0" type="left link" link="21" vehicle="2"  />
	<event time="33810.0" type="entered link" link="22" vehicle="2"  />
	<event time="34409.0" type="actend" person="4" link="20" actType="w"  />
	<event time="34409.0" type="departure" person="4" link="20" legMode="car"  />
	<event time="34409.0" type="PersonEntersVehicle" person="4" vehicle="4"  />
	<event time="34409.0" type="vehicle enters traffic" person="4" link="20" vehicle="4" networkMode="car" relativePosition="1.0"  />
	<event time="34410.0" type="left link" link="20" vehicle="4"  />
	<event time="34410.0" type="entered link" link="21" vehicle="4"  />
	<event time="35010.0" type="left link" link="21" vehicle="4"  />
	<event time="35010.0" type="entered link" link="22" vehicle="4"  />
	<event time="35910.0" type="left link" link="22" vehicle="2"  />
	<event time="35910.0" type="entered link" link="23" vehicle="2"  />
	<event time="36510.0" type="left link" link="23" vehicle="2"  />
	<event time="36510.0" type="entered link" link="1" vehicle="2"  />
	<event time="37109.0" type="vehicle leaves traffic" person="2" link="1" vehicle="2" networkMode="car" relativePosition="1.0"  />
	<event time="37109.0" type="PersonLeavesVehicle" person="2" vehicle="2"  />
	<event time="37109.0" type="arrival" person="2" link="1" legMode="car"  />
	<event time="37109.0" type="actstart" person="2" link="1" x="-25000.0" y="0.0" actType="h"  />
	<event time="37110.0" type="left link" link="22" vehicle="4"  />
	<event time="37110.0" type="entered link" link="23" vehicle="4"  />
	<event time="37710.0" type="left link" link="23" vehicle="4"  />
	<event time="37710.0" type="entered link" link="1" vehicle="4"  />
	<event time="38309.0" type="vehicle leaves traffic" person="4" link="1" vehicle="4" networkMode="car" relativePosition="1.0"  />
	<event time="38309.0" type="PersonLeavesVehicle" person="4" vehicle="4"  />
	<event time="38309.0" type="arrival" person="4" link="1" legMode="car"  />
	<event time="38309.0" type="actstart" person="4" link="1" x="-25000.0" y="0.0" actType="h"  />
	<event time="46500.0" type="actend" person="5" link="20" actType="w"  />
	<event time="46500.0" type="departure" person="5" link="20" legMode="car"  />
	<event time="46500.0" type="PersonEntersVehicle" person="5" vehicle="5"  />
	<event time="46500.0" type="vehicle enters traffic" person="5" link="20" vehicle="5" networkMode="car" relativePosition="1.0"  />
	<event time="46501.0" type="left link" link="20" vehicle="5"  />
	<event time="46501.0" type="entered link" link="21" vehicle="5"  />
	<event time="47101.0" type="left link" link="21" vehicle="5"  />
	<event time="47101.0" type="entered link" link="22" vehicle="5"  />
	<event time="49201.0" type="left link" link="22" vehicle="5"  />
	<event time="49201.0" type="entered link" link="23" vehicle="5"  />
	<event time="49801.0" type="left link" link="23" vehicle="5"  />
	<event time="49801.0" type="entered link" link="1" vehicle="5"  />
	<event time="50400.0" type="vehicle leaves traffic" person="5" link="1" vehicle="5" networkMode="car" relativePosition="1.0"  />
	<event time="50400.0" type="PersonLeavesVehicle" person="5" vehicle="5"  />
	<event time="50400.0" type="arrival" person="5" link="1" legMode="car"  />
	<event time="50400.0" type="actstart" person="5" link="1" x="-25000.0" y="0.0" actType="h"  />
</events>